drf_plus/__init__.py
drf_plus/utils.py
drf_plus/files/__init__.py
drf_plus/files/sample/__init__.py
drf_plus/files/sample/admin.py
drf_plus/files/sample/apps.py
drf_plus/files/sample/backends.py
drf_plus/files/sample/filters.py
drf_plus/files/sample/middlewares.py
drf_plus/files/sample/migrations.py
drf_plus/files/sample/models.py
drf_plus/files/sample/openapi.py
drf_plus/files/sample/paginations.py
drf_plus/files/sample/permissions.py
drf_plus/files/sample/router.py
drf_plus/files/sample/serializers.py
drf_plus/files/sample/settings.py
drf_plus/files/sample/signals.py
drf_plus/files/sample/spectacular_hooks.py
drf_plus/files/sample/tests.py
drf_plus/files/sample/views.py
drf_plus/management/__init__.py
drf_plus/management/app_template/__init__.py
drf_plus/management/app_template/admin.py
drf_plus/management/app_template/apps.py
drf_plus/management/app_template/models.py
drf_plus/management/app_template/migrations/__init__.py
drf_plus/management/app_template/v1/__init__.py
drf_plus/management/app_template/v1/filters.py
drf_plus/management/app_template/v1/serializers.py
drf_plus/management/app_template/v1/tests.py
drf_plus/management/app_template/v1/urls.py
drf_plus/management/app_template/v1/views.py
drf_plus/management/commands/__init__.py
drf_plus/management/commands/dummy.py
drf_plus/management/commands/sample.py
drf_plus/management/commands/startapp.py
drf_plus-0.2.4.dist-info/METADATA
drf_plus-0.2.4.dist-info/WHEEL
drf_plus-0.2.4.dist-info/top_level.txt
drf_plus-0.2.4.dist-info/RECORD
